LICENSE
MANIFEST.in
README.md
setup.py
docs/index.md
epic_admin/__init__.py
epic_admin/admin.py
epic_admin/apps.py
epic_admin/helpers.py
epic_admin/models.py
epic_admin/signals.py
epic_admin/site.py
epic_admin/version.py
epic_admin.egg-info/PKG-INFO
epic_admin.egg-info/SOURCES.txt
epic_admin.egg-info/dependency_links.txt
epic_admin.egg-info/top_level.txt
epic_admin/migrations/0001_initial.py
epic_admin/migrations/0002_auto_20190806_1814.py
epic_admin/migrations/0003_delete_userprofile.py
epic_admin/migrations/0004_organization_userprofile.py
epic_admin/migrations/0005_auto_20190807_1431.py
epic_admin/migrations/__init__.py
epic_admin/templatetags/__init__.py
epic_admin/templatetags/epic_utils.py