Metadata-Version: 1.1
Name: epic-admin
Version: 1.0.1
Summary: Custom django admin
Home-page: https://github.com/sasri-djproject/epic_admin
Author: Rizki Sasri Dwitama
Author-email: sasri.djproject@gmail.com
License: MIT License
Platform: UNKNOWN
Classifier: Environment :: Web Environment
Classifier: Framework :: Django
Classifier: Framework :: Django :: 2.2
Classifier: License :: OSI Approved :: MIT License
Classifier: Operating System :: OS Independent
Classifier: Programming Language :: Python
Classifier: Programming Language :: Python :: 3.6
Classifier: Programming Language :: Python :: 3.7
Classifier: Topic :: Internet :: WWW/HTTP
Classifier: Topic :: Internet :: WWW/HTTP :: Dynamic Content
